watchmen_pipeline_kernel/__init__.py
watchmen_pipeline_kernel/boot/__init__.py
watchmen_pipeline_kernel/boot/boot.py
watchmen_pipeline_kernel/cache/__init__.py
watchmen_pipeline_kernel/cache/cache_service.py
watchmen_pipeline_kernel/cache/compiled_pipeline_cache.py
watchmen_pipeline_kernel/common/__init__.py
watchmen_pipeline_kernel/common/exception.py
watchmen_pipeline_kernel/common/settings.py
watchmen_pipeline_kernel/external_writer/__init__.py
watchmen_pipeline_kernel/external_writer/elastic_search_writer.py
watchmen_pipeline_kernel/external_writer/kafka_writer.py
watchmen_pipeline_kernel/external_writer/prebuilt_writers.py
watchmen_pipeline_kernel/external_writer/standard_writer.py
watchmen_pipeline_kernel/monitor_log/__init__.py
watchmen_pipeline_kernel/monitor_log/monitor_log_data_service.py
watchmen_pipeline_kernel/pipeline/__init__.py
watchmen_pipeline_kernel/pipeline/monitor_log_invoker.py
watchmen_pipeline_kernel/pipeline/pipeline_invoker.py
watchmen_pipeline_kernel/pipeline/pipeline_trigger.py
watchmen_pipeline_kernel/pipeline/pipelines_dispatcher.py
watchmen_pipeline_kernel/pipeline/sql_performance_invoker.py
watchmen_pipeline_kernel/pipeline_schema/__init__.py
watchmen_pipeline_kernel/pipeline_schema/compiled_action.py
watchmen_pipeline_kernel/pipeline_schema/compiled_pipeline.py
watchmen_pipeline_kernel/pipeline_schema/compiled_single_unit.py
watchmen_pipeline_kernel/pipeline_schema/compiled_stage.py
watchmen_pipeline_kernel/pipeline_schema/compiled_unit.py
watchmen_pipeline_kernel/pipeline_schema/distributed_compiled_unit.py
watchmen_pipeline_kernel/pipeline_schema/pipeline_context.py
watchmen_pipeline_kernel/pipeline_schema_interface/__init__.py
watchmen_pipeline_kernel/pipeline_schema_interface/compiled_pipeline.py
watchmen_pipeline_kernel/pipeline_schema_interface/create_queue_pipeline.py
watchmen_pipeline_kernel/pipeline_schema_interface/pipeline_context.py
watchmen_pipeline_kernel/pipeline_schema_interface/topic_storages.py
watchmen_pipeline_kernel-18.0.1.dist-info/METADATA
watchmen_pipeline_kernel-18.0.1.dist-info/WHEEL
watchmen_pipeline_kernel-18.0.1.dist-info/licenses/LICENSE
watchmen_pipeline_kernel-18.0.1.dist-info/RECORD
