Metadata-Version: 2.4
Name: watchmen-pipeline-kernel
Version: 18.0.1
Summary: 
License: MIT
License-File: LICENSE
Author: botlikes
Author-email: 75356972+botlikes456@users.noreply.github.com
Requires-Python: >=3.12,<3.13
Classifier: License :: OSI Approved :: MIT License
Classifier: Programming Language :: Python :: 3
Classifier: Programming Language :: Python :: 3.12
Provides-Extra: es-ext-writer
Provides-Extra: kafka-ext-writer
Provides-Extra: mongodb
Provides-Extra: mssql
Provides-Extra: mysql
Provides-Extra: oracle
Provides-Extra: postgresql
Provides-Extra: standard-ext-writer
Requires-Dist: APScheduler (>=3.10.4,<4.0.0)
Requires-Dist: aiokafka (>=0.12.0,<0.13.0) ; extra == "kafka-ext-writer"
Requires-Dist: dask (>=2024.7.0,<2025.0.0)
Requires-Dist: distributed (>=2024.7.0,<2025.0.0)
Requires-Dist: requests (>=2.32.3,<3.0.0) ; extra == "standard-ext-writer"
Requires-Dist: watchmen-data-kernel (==18.0.1)
Requires-Dist: watchmen-storage-mongodb (==18.0.1) ; extra == "mongodb"
Requires-Dist: watchmen-storage-mssql (==18.0.1) ; extra == "mssql"
Requires-Dist: watchmen-storage-mysql (==18.0.1) ; extra == "mysql"
Requires-Dist: watchmen-storage-oracle (==18.0.1) ; extra == "oracle"
Requires-Dist: watchmen-storage-postgresql (==18.0.1) ; extra == "postgresql"
